Products.pipbox-configure.zcml
README.txt
ignores.txt
setup.py
Products/__init__.py
Products.pipbox.egg-info/PKG-INFO
Products.pipbox.egg-info/SOURCES.txt
Products.pipbox.egg-info/dependency_links.txt
Products.pipbox.egg-info/entry_points.txt
Products.pipbox.egg-info/namespace_packages.txt
Products.pipbox.egg-info/not-zip-safe
Products.pipbox.egg-info/requires.txt
Products.pipbox.egg-info/top_level.txt
Products/pipbox/HISTORY.txt
Products/pipbox/README.txt
Products/pipbox/TODO.txt
Products/pipbox/__init__.py
Products/pipbox/configure.zcml
Products/pipbox/profiles.zcml
Products/pipbox/setuphandlers.py
Products/pipbox/tests.py
Products/pipbox/version.txt
Products/pipbox/browser/__init__.py
Products/pipbox/browser/configure.zcml
Products/pipbox/browser/interfaces.py
Products/pipbox/browser/jsinit.py
Products/pipbox/browser/stylesheet.py
Products/pipbox/browser/resources/pipbox.js
Products/pipbox/browser/resources/images/close.png
Products/pipbox/browser/templates/ajax_template.pt
Products/pipbox/browser/templates/pipbox.css.dtml
Products/pipbox/profiles/default/Products.pipbox_various.txt
Products/pipbox/profiles/default/cssregistry.xml
Products/pipbox/profiles/default/import_steps.xml
Products/pipbox/profiles/default/jsregistry.xml
Products/pipbox/profiles/default/metadata.xml
Products/pipbox/profiles/default/propertiestool.xml
Products/pipbox/profiles/default/skins.xml
Products/pipbox/profiles/default/viewlets.xml
Products/pipbox/skins/pipbox/popupforms.js
docs/INSTALL.txt
docs/LICENSE.GPL
docs/LICENSE.txt