Metadata-Version: 1.0
Name: Products.pipbox
Version: 1.0b2
Summary: Picture In Picture (lightbox/greybox) support for Plone
Home-page: http://svn.plone.org/svn/collective/Products.pipbox
Author: Steve McMahon
Author-email: steve@dcn.org
License: GPL
Keywords: web zope plone theme
Platform: UNKNOWN
Classifier: Framework :: Plone
Classifier: Programming Language :: Python
Classifier: Topic :: Software Development :: Libraries :: Python Modules
